random_generator_5bits.vhd
library ieee;
use ieee.std_logic_1164.all;


entity random_generator_5bits is
    port(
        clock: in std_logic;
        enable: in std_logic;
        dado: out std_logic_vector(4 downto 0)
    );
end entity random_generator_5bits;

architecture LFSR of random_generator_5bits is
    signal dado28: std_logic_vector(27 downto 0) := "1010110101101011010110101101";
    signal dado28prox: std_logic_vector(27 downto 0);

begin
    process(clock)
    begin
        if (clock'event and clock='1' and enable='1') then
            dado28 <= dado28prox;
        end if;
    end process;

    GEN: for i in 3 to 26 generate
            dado28prox(i+1) <= dado28(i);
        end generate;

    dado28prox(3) <= dado28(27) xor dado28(2);

    dado28prox(2) <= dado28(1);
    dado28prox(1) <= dado28(0);
    dado28prox(0) <= dado28(27);

    dado <= dado28(4 downto 0);
end architecture;

random_generator_tb.vhd
library ieee;
use ieee.std_logic_1164.all;
use std.textio.all;

-- entidade do testbench
entity random_generator_tb is
end entity;

architecture tb of random_generator_tb is
    component random_generator_5bits is
        port(
            clock: in std_logic;
            enable: in std_logic;
            dado: out std_logic_vector(4 downto 0)
        );
    end component;


    signal enable_in: std_logic;
    signal clk_in: std_logic := '0';
    signal dado_out: std_logic_vector(4 downto 0);

    -- Configurações do clock
  signal keep_simulating: std_logic := '0'; -- delimita o tempo de geração do clock
  constant clockPeriod : time := 20 ns;     -- frequencia 50MHz
begin
    clk_in <= (not clk_in) and keep_simulating after clockPeriod/2;
    DUT: random_generator_5bits port map(
        clock => clk_in,
        enable => enable_in,
        dado => dado_out
    );

    stimulus: process is    
    begin
        assert false report "inicio da simulacao" severity note;
        keep_simulating <= '1';  -- inicia geracao do sinal de clock
        
        enable_in <= '1';
        wait for 500*clockPeriod;
        ---- final do testbench
        assert false report "fim da simulacao" severity note;
        keep_simulating <= '0';
        wait;
    end process;

end architecture;

random_test1.vcd
$date
  Sat Apr  1 17:16:49 2023
$end
$version
  GHDL v0
$end
$timescale
  1 fs
$end
$scope module standard $end
$upscope $end
$scope module std_logic_1164 $end
$upscope $end
$scope module textio $end
$upscope $end
$scope module random_generator_tb $end
$var reg 1 ! enable_in $end
$var reg 1 " clk_in $end
$var reg 5 # dado_out[4:0] $end
$var reg 1 $ keep_simulating $end
$scope module dut $end
$var reg 1 % clock $end
$var reg 1 & enable $end
$var reg 5 ' dado[4:0] $end
$var reg 28 ( dado28[27:0] $end
$var reg 28 ) dado28prox[27:0] $end
$scope module gen(3) $end
$upscope $end
$scope module gen(4) $end
$upscope $end
$scope module gen(5) $end
$upscope $end
$scope module gen(6) $end
$upscope $end
$scope module gen(7) $end
$upscope $end
$scope module gen(8) $end
$upscope $end
$scope module gen(9) $end
$upscope $end
$scope module gen(10) $end
$upscope $end
$scope module gen(11) $end
$upscope $end
$scope module gen(12) $end
$upscope $end
$scope module gen(13) $end
$upscope $end
$scope module gen(14) $end
$upscope $end
$scope module gen(15) $end
$upscope $end
$scope module gen(16) $end
$upscope $end
$scope module gen(17) $end
$upscope $end
$scope module gen(18) $end
$upscope $end
$scope module gen(19) $end
$upscope $end
$scope module gen(20) $end
$upscope $end
$scope module gen(21) $end
$upscope $end
$scope module gen(22) $end
$upscope $end
$scope module gen(23) $end
$upscope $end
$scope module gen(24) $end
$upscope $end
$scope module gen(25) $end
$upscope $end
$scope module gen(26) $end
$upscope $end
$upscope $end
$upscope $end
$enddefinitions $end
#0
1!
0"
b01101 #
1$
0%
1&
b01101 '
b1010110101101011010110101101 (
b0101101011010110101101010011 )
#10000000
1"
b10011 #
1%
b10011 '
b0101101011010110101101010011 (
b1011010110101101011010100110 )
#20000000
0"
0%
#30000000
1"
b00110 #
1%
b00110 '
b1011010110101101011010100110 (
b0110101101011010110101000101 )
#40000000
0"
0%
#50000000
1"
b00101 #
1%
b00101 '
b0110101101011010110101000101 (
b1101011010110101101010001010 )
#60000000
0"
0%
#70000000
1"
b01010 #
1%
b01010 '
b1101011010110101101010001010 (
b1010110101101011010100011101 )
#80000000
0"
0%
#90000000
1"
b11101 #
1%
b11101 '
b1010110101101011010100011101 (
b0101101011010110101000110011 )
#100000000
0"
0%
#110000000
1"
b10011 #
1%
b10011 '
b0101101011010110101000110011 (
b1011010110101101010001100110 )
#120000000
0"
0%
#130000000
1"
b00110 #
1%
b00110 '
b1011010110101101010001100110 (
b0110101101011010100011000101 )
#140000000
0"
0%
#150000000
1"
b00101 #
1%
b00101 '
b0110101101011010100011000101 (
b1101011010110101000110001010 )
#160000000
0"
0%
#170000000
1"
b01010 #
1%
b01010 '
b1101011010110101000110001010 (
b1010110101101010001100011101 )
#180000000
0"
0%
#190000000
1"
b11101 #
1%
b11101 '
b1010110101101010001100011101 (
b0101101011010100011000110011 )
#200000000
0"
0%
#210000000
1"
b10011 #
1%
b10011 '
b0101101011010100011000110011 (
b1011010110101000110001100110 )
#220000000
0"
0%
#230000000
1"
b00110 #
1%
b00110 '
b1011010110101000110001100110 (
b0110101101010001100011000101 )
#240000000
0"
0%
#250000000
1"
b00101 #
1%
b00101 '
b0110101101010001100011000101 (
b1101011010100011000110001010 )
#260000000
0"
0%
#270000000
1"
b01010 #
1%
b01010 '
b1101011010100011000110001010 (
b1010110101000110001100011101 )
#280000000
0"
0%
#290000000
1"
b11101 #
1%
b11101 '
b1010110101000110001100011101 (
b0101101010001100011000110011 )
#300000000
0"
0%
#310000000
1"
b10011 #
1%
b10011 '
b0101101010001100011000110011 (
b1011010100011000110001100110 )
#320000000
0"
0%
#330000000
1"
b00110 #
1%
b00110 '
b1011010100011000110001100110 (
b0110101000110001100011000101 )
#340000000
0"
0%
#350000000
1"
b00101 #
1%
b00101 '
b0110101000110001100011000101 (
b1101010001100011000110001010 )
#360000000
0"
0%
#370000000
1"
b01010 #
1%
b01010 '
b1101010001100011000110001010 (
b1010100011000110001100011101 )
#380000000
0"
0%
#390000000
1"
b11101 #
1%
b11101 '
b1010100011000110001100011101 (
b0101000110001100011000110011 )
#400000000
0"
0%
#410000000
1"
b10011 #
1%
b10011 '
b0101000110001100011000110011 (
b1010001100011000110001100110 )
#420000000
0"
0%
#430000000
1"
b00110 #
1%
b00110 '
b1010001100011000110001100110 (
b0100011000110001100011000101 )
#440000000
0"
0%
#450000000
1"
b00101 #
1%
b00101 '
b0100011000110001100011000101 (
b1000110001100011000110001010 )
#460000000
0"
0%
#470000000
1"
b01010 #
1%
b01010 '
b1000110001100011000110001010 (
b0001100011000110001100011101 )
#480000000
0"
0%
#490000000
1"
b11101 #
1%
b11101 '
b0001100011000110001100011101 (
b0011000110001100011000111010 )
#500000000
0"
0%
#510000000
1"
b11010 #
1%
b11010 '
b0011000110001100011000111010 (
b0110001100011000110001110100 )
#520000000
0"
0%
#530000000
1"
b10100 #
1%
b10100 '
b0110001100011000110001110100 (
b1100011000110001100011101000 )
#540000000
0"
0%
#550000000
1"
b01000 #
1%
b01000 '
b1100011000110001100011101000 (
b1000110001100011000111011001 )
#560000000
0"
0%
#570000000
1"
b11001 #
1%
b11001 '
b1000110001100011000111011001 (
b0001100011000110001110111011 )
#580000000
0"
0%
#590000000
1"
b11011 #
1%
b11011 '
b0001100011000110001110111011 (
b0011000110001100011101110110 )
#600000000
0"
0%
#610000000
1"
b10110 #
1%
b10110 '
b0011000110001100011101110110 (
b0110001100011000111011101100 )
#620000000
0"
0%
#630000000
1"
b01100 #
1%
b01100 '
b0110001100011000111011101100 (
b1100011000110001110111011000 )
#640000000
0"
0%
#650000000
1"
b11000 #
1%
b11000 '
b1100011000110001110111011000 (
b1000110001100011101110111001 )
#660000000
0"
0%
#670000000
1"
b11001 #
1%
b11001 '
b1000110001100011101110111001 (
b0001100011000111011101111011 )
#680000000
0"
0%
#690000000
1"
b11011 #
1%
b11011 '
b0001100011000111011101111011 (
b0011000110001110111011110110 )
#700000000
0"
0%
#710000000
1"
b10110 #
1%
b10110 '
b0011000110001110111011110110 (
b0110001100011101110111101100 )
#720000000
0"
0%
#730000000
1"
b01100 #
1%
b01100 '
b0110001100011101110111101100 (
b1100011000111011101111011000 )
#740000000
0"
0%
#750000000
1"
b11000 #
1%
b11000 '
b1100011000111011101111011000 (
b1000110001110111011110111001 )
#760000000
0"
0%
#770000000
1"
b11001 #
1%
b11001 '
b1000110001110111011110111001 (
b0001100011101110111101111011 )
#780000000
0"
0%
#790000000
1"
b11011 #
1%
b11011 '
b0001100011101110111101111011 (
b0011000111011101111011110110 )
#800000000
0"
0%
#810000000
1"
b10110 #
1%
b10110 '
b0011000111011101111011110110 (
b0110001110111011110111101100 )
#820000000
0"
0%
#830000000
1"
b01100 #
1%
b01100 '
b0110001110111011110111101100 (
b1100011101110111101111011000 )
#840000000
0"
0%
#850000000
1"
b11000 #
1%
b11000 '
b1100011101110111101111011000 (
b1000111011101111011110111001 )
#860000000
0"
0%
#870000000
1"
b11001 #
1%
b11001 '
b1000111011101111011110111001 (
b0001110111011110111101111011 )
#880000000
0"
0%
#890000000
1"
b11011 #
1%
b11011 '
b0001110111011110111101111011 (
b0011101110111101111011110110 )
#900000000
0"
0%
#910000000
1"
b10110 #
1%
b10110 '
b0011101110111101111011110110 (
b0111011101111011110111101100 )
#920000000
0"
0%
#930000000
1"
b01100 #
1%
b01100 '
b0111011101111011110111101100 (
b1110111011110111101111011000 )
#940000000
0"
0%
#950000000
1"
b11000 #
1%
b11000 '
b1110111011110111101111011000 (
b1101110111101111011110111001 )
#960000000
0"
0%
#970000000
1"
b11001 #
1%
b11001 '
b1101110111101111011110111001 (
b1011101111011110111101111011 )
#980000000
0"
0%
#990000000
1"
b11011 #
1%
b11011 '
b1011101111011110111101111011 (
b0111011110111101111011111111 )
#1000000000
0"
0%
#1010000000
1"
b11111 #
1%
b11111 '
b0111011110111101111011111111 (
b1110111101111011110111111110 )
#1020000000
0"
0%
#1030000000
1"
b11110 #
1%
b11110 '
b1110111101111011110111111110 (
b1101111011110111101111110101 )
#1040000000
0"
0%
#1050000000
1"
b10101 #
1%
b10101 '
b1101111011110111101111110101 (
b1011110111101111011111100011 )
#1060000000
0"
0%
#1070000000
1"
b00011 #
1%
b00011 '
b1011110111101111011111100011 (
b0111101111011110111111001111 )
#1080000000
0"
0%
#1090000000
1"
b01111 #
1%
b01111 '
b0111101111011110111111001111 (
b1111011110111101111110011110 )
#1100000000
0"
0%
#1110000000
1"
b11110 #
1%
b11110 '
b1111011110111101111110011110 (
b1110111101111011111100110101 )
#1120000000
0"
0%
#1130000000
1"
b10101 #
1%
b10101 '
b1110111101111011111100110101 (
b1101111011110111111001100011 )
#1140000000
0"
0%
#1150000000
1"
b00011 #
1%
b00011 '
b1101111011110111111001100011 (
b1011110111101111110011001111 )
#1160000000
0"
0%
#1170000000
1"
b01111 #
1%
b01111 '
b1011110111101111110011001111 (
b0111101111011111100110010111 )
#1180000000
0"
0%
#1190000000
1"
b10111 #
1%
b10111 '
b0111101111011111100110010111 (
b1111011110111111001100101110 )
#1200000000
0"
0%
#1210000000
1"
b01110 #
1%
b01110 '
b1111011110111111001100101110 (
b1110111101111110011001010101 )
#1220000000
0"
0%
#1230000000
1"
b10101 #
1%
b10101 '
b1110111101111110011001010101 (
b1101111011111100110010100011 )
#1240000000
0"
0%
#1250000000
1"
b00011 #
1%
b00011 '
b1101111011111100110010100011 (
b1011110111111001100101001111 )
#1260000000
0"
0%
#1270000000
1"
b01111 #
1%
b01111 '
b1011110111111001100101001111 (
b0111101111110011001010010111 )
#1280000000
0"
0%
#1290000000
1"
b10111 #
1%
b10111 '
b0111101111110011001010010111 (
b1111011111100110010100101110 )
#1300000000
0"
0%
#1310000000
1"
b01110 #
1%
b01110 '
b1111011111100110010100101110 (
b1110111111001100101001010101 )
#1320000000
0"
0%
#1330000000
1"
b10101 #
1%
b10101 '
b1110111111001100101001010101 (
b1101111110011001010010100011 )
#1340000000
0"
0%
#1350000000
1"
b00011 #
1%
b00011 '
b1101111110011001010010100011 (
b1011111100110010100101001111 )
#1360000000
0"
0%
#1370000000
1"
b01111 #
1%
b01111 '
b1011111100110010100101001111 (
b0111111001100101001010010111 )
#1380000000
0"
0%
#1390000000
1"
b10111 #
1%
b10111 '
b0111111001100101001010010111 (
b1111110011001010010100101110 )
#1400000000
0"
0%
#1410000000
1"
b01110 #
1%
b01110 '
b1111110011001010010100101110 (
b1111100110010100101001010101 )
#1420000000
0"
0%
#1430000000
1"
b10101 #
1%
b10101 '
b1111100110010100101001010101 (
b1111001100101001010010100011 )
#1440000000
0"
0%
#1450000000
1"
b00011 #
1%
b00011 '
b1111001100101001010010100011 (
b1110011001010010100101001111 )
#1460000000
0"
0%
#1470000000
1"
b01111 #
1%
b01111 '
b1110011001010010100101001111 (
b1100110010100101001010010111 )
#1480000000
0"
0%
#1490000000
1"
b10111 #
1%
b10111 '
b1100110010100101001010010111 (
b1001100101001010010100100111 )
#1500000000
0"
0%
#1510000000
1"
b00111 #
1%
b00111 '
b1001100101001010010100100111 (
b0011001010010100101001000111 )
#1520000000
0"
0%
#1530000000
1"
1%
b0011001010010100101001000111 (
b0110010100101001010010001110 )
#1540000000
0"
0%
#1550000000
1"
b01110 #
1%
b01110 '
b0110010100101001010010001110 (
b1100101001010010100100011100 )
#1560000000
0"
0%
#1570000000
1"
b11100 #
1%
b11100 '
b1100101001010010100100011100 (
b1001010010100101001000110001 )
#1580000000
0"
0%
#1590000000
1"
b10001 #
1%
b10001 '
b1001010010100101001000110001 (
b0010100101001010010001101011 )
#1600000000
0"
0%
#1610000000
1"
b01011 #
1%
b01011 '
b0010100101001010010001101011 (
b0101001010010100100011010110 )
#1620000000
0"
0%
#1630000000
1"
b10110 #
1%
b10110 '
b0101001010010100100011010110 (
b1010010100101001000110101100 )
#1640000000
0"
0%
#1650000000
1"
b01100 #
1%
b01100 '
b1010010100101001000110101100 (
b0100101001010010001101010001 )
#1660000000
0"
0%
#1670000000
1"
b10001 #
1%
b10001 '
b0100101001010010001101010001 (
b1001010010100100011010100010 )
#1680000000
0"
0%
#1690000000
1"
b00010 #
1%
b00010 '
b1001010010100100011010100010 (
b0010100101001000110101001101 )
#1700000000
0"
0%
#1710000000
1"
b01101 #
1%
b01101 '
b0010100101001000110101001101 (
b0101001010010001101010011010 )
#1720000000
0"
0%
#1730000000
1"
b11010 #
1%
b11010 '
b0101001010010001101010011010 (
b1010010100100011010100110100 )
#1740000000
0"
0%
#1750000000
1"
b10100 #
1%
b10100 '
b1010010100100011010100110100 (
b0100101001000110101001100001 )
#1760000000
0"
0%
#1770000000
1"
b00001 #
1%
b00001 '
b0100101001000110101001100001 (
b1001010010001101010011000010 )
#1780000000
0"
0%
#1790000000
1"
b00010 #
1%
b00010 '
b1001010010001101010011000010 (
b0010100100011010100110001101 )
#1800000000
0"
0%
#1810000000
1"
b01101 #
1%
b01101 '
b0010100100011010100110001101 (
b0101001000110101001100011010 )
#1820000000
0"
0%
#1830000000
1"
b11010 #
1%
b11010 '
b0101001000110101001100011010 (
b1010010001101010011000110100 )
#1840000000
0"
0%
#1850000000
1"
b10100 #
1%
b10100 '
b1010010001101010011000110100 (
b0100100011010100110001100001 )
#1860000000
0"
0%
#1870000000
1"
b00001 #
1%
b00001 '
b0100100011010100110001100001 (
b1001000110101001100011000010 )
#1880000000
0"
0%
#1890000000
1"
b00010 #
1%
b00010 '
b1001000110101001100011000010 (
b0010001101010011000110001101 )
#1900000000
0"
0%
#1910000000
1"
b01101 #
1%
b01101 '
b0010001101010011000110001101 (
b0100011010100110001100011010 )
#1920000000
0"
0%
#1930000000
1"
b11010 #
1%
b11010 '
b0100011010100110001100011010 (
b1000110101001100011000110100 )
#1940000000
0"
0%
#1950000000
1"
b10100 #
1%
b10100 '
b1000110101001100011000110100 (
b0001101010011000110001100001 )
#1960000000
0"
0%
#1970000000
1"
b00001 #
1%
b00001 '
b0001101010011000110001100001 (
b0011010100110001100011000010 )
#1980000000
0"
0%
#1990000000
1"
b00010 #
1%
b00010 '
b0011010100110001100011000010 (
b0110101001100011000110000100 )
#2000000000
0"
0%
#2010000000
1"
b00100 #
1%
b00100 '
b0110101001100011000110000100 (
b1101010011000110001100001000 )
#2020000000
0"
0%
#2030000000
1"
b01000 #
1%
b01000 '
b1101010011000110001100001000 (
b1010100110001100011000011001 )
#2040000000
0"
0%
#2050000000
1"
b11001 #
1%
b11001 '
b1010100110001100011000011001 (
b0101001100011000110000111011 )
#2060000000
0"
0%
#2070000000
1"
b11011 #
1%
b11011 '
b0101001100011000110000111011 (
b1010011000110001100001110110 )
#2080000000
0"
0%
#2090000000
1"
b10110 #
1%
b10110 '
b1010011000110001100001110110 (
b0100110001100011000011100101 )
#2100000000
0"
0%
#2110000000
1"
b00101 #
1%
b00101 '
b0100110001100011000011100101 (
b1001100011000110000111001010 )
#2120000000
0"
0%
#2130000000
1"
b01010 #
1%
b01010 '
b1001100011000110000111001010 (
b0011000110001100001110011101 )
#2140000000
0"
0%
#2150000000
1"
b11101 #
1%
b11101 '
b0011000110001100001110011101 (
b0110001100011000011100111010 )
#2160000000
0"
0%
#2170000000
1"
b11010 #
1%
b11010 '
b0110001100011000011100111010 (
b1100011000110000111001110100 )
#2180000000
0"
0%
#2190000000
1"
b10100 #
1%
b10100 '
b1100011000110000111001110100 (
b1000110001100001110011100001 )
#2200000000
0"
0%
#2210000000
1"
b00001 #
1%
b00001 '
b1000110001100001110011100001 (
b0001100011000011100111001011 )
#2220000000
0"
0%
#2230000000
1"
b01011 #
1%
b01011 '
b0001100011000011100111001011 (
b0011000110000111001110010110 )
#2240000000
0"
0%
#2250000000
1"
b10110 #
1%
b10110 '
b0011000110000111001110010110 (
b0110001100001110011100101100 )
#2260000000
0"
0%
#2270000000
1"
b01100 #
1%
b01100 '
b0110001100001110011100101100 (
b1100011000011100111001011000 )
#2280000000
0"
0%
#2290000000
1"
b11000 #
1%
b11000 '
b1100011000011100111001011000 (
b1000110000111001110010111001 )
#2300000000
0"
0%
#2310000000
1"
b11001 #
1%
b11001 '
b1000110000111001110010111001 (
b0001100001110011100101111011 )
#2320000000
0"
0%
#2330000000
1"
b11011 #
1%
b11011 '
b0001100001110011100101111011 (
b0011000011100111001011110110 )
#2340000000
0"
0%
#2350000000
1"
b10110 #
1%
b10110 '
b0011000011100111001011110110 (
b0110000111001110010111101100 )
#2360000000
0"
0%
#2370000000
1"
b01100 #
1%
b01100 '
b0110000111001110010111101100 (
b1100001110011100101111011000 )
#2380000000
0"
0%
#2390000000
1"
b11000 #
1%
b11000 '
b1100001110011100101111011000 (
b1000011100111001011110111001 )
#2400000000
0"
0%
#2410000000
1"
b11001 #
1%
b11001 '
b1000011100111001011110111001 (
b0000111001110010111101111011 )
#2420000000
0"
0%
#2430000000
1"
b11011 #
1%
b11011 '
b0000111001110010111101111011 (
b0001110011100101111011110110 )
#2440000000
0"
0%
#2450000000
1"
b10110 #
1%
b10110 '
b0001110011100101111011110110 (
b0011100111001011110111101100 )
#2460000000
0"
0%
#2470000000
1"
b01100 #
1%
b01100 '
b0011100111001011110111101100 (
b0111001110010111101111011000 )
#2480000000
0"
0%
#2490000000
1"
b11000 #
1%
b11000 '
b0111001110010111101111011000 (
b1110011100101111011110110000 )
#2500000000
0"
0%
#2510000000
1"
b10000 #
1%
b10000 '
b1110011100101111011110110000 (
b1100111001011110111101101001 )
#2520000000
0"
0%
#2530000000
1"
b01001 #
1%
b01001 '
b1100111001011110111101101001 (
b1001110010111101111011011011 )
#2540000000
0"
0%
#2550000000
1"
b11011 #
1%
b11011 '
b1001110010111101111011011011 (
b0011100101111011110110111111 )
#2560000000
0"
0%
#2570000000
1"
b11111 #
1%
b11111 '
b0011100101111011110110111111 (
b0111001011110111101101111110 )
#2580000000
0"
0%
#2590000000
1"
b11110 #
1%
b11110 '
b0111001011110111101101111110 (
b1110010111101111011011111100 )
#2600000000
0"
0%
#2610000000
1"
b11100 #
1%
b11100 '
b1110010111101111011011111100 (
b1100101111011110110111110001 )
#2620000000
0"
0%
#2630000000
1"
b10001 #
1%
b10001 '
b1100101111011110110111110001 (
b1001011110111101101111101011 )
#2640000000
0"
0%
#2650000000
1"
b01011 #
1%
b01011 '
b1001011110111101101111101011 (
b0010111101111011011111011111 )
#2660000000
0"
0%
#2670000000
1"
b11111 #
1%
b11111 '
b0010111101111011011111011111 (
b0101111011110110111110111110 )
#2680000000
0"
0%
#2690000000
1"
b11110 #
1%
b11110 '
b0101111011110110111110111110 (
b1011110111101101111101111100 )
#2700000000
0"
0%
#2710000000
1"
b11100 #
1%
b11100 '
b1011110111101101111101111100 (
b0111101111011011111011110001 )
#2720000000
0"
0%
#2730000000
1"
b10001 #
1%
b10001 '
b0111101111011011111011110001 (
b1111011110110111110111100010 )
#2740000000
0"
0%
#2750000000
1"
b00010 #
1%
b00010 '
b1111011110110111110111100010 (
b1110111101101111101111001101 )
#2760000000
0"
0%
#2770000000
1"
b01101 #
1%
b01101 '
b1110111101101111101111001101 (
b1101111011011111011110010011 )
#2780000000
0"
0%
#2790000000
1"
b10011 #
1%
b10011 '
b1101111011011111011110010011 (
b1011110110111110111100101111 )
#2800000000
0"
0%
#2810000000
1"
b01111 #
1%
b01111 '
b1011110110111110111100101111 (
b0111101101111101111001010111 )
#2820000000
0"
0%
#2830000000
1"
b10111 #
1%
b10111 '
b0111101101111101111001010111 (
b1111011011111011110010101110 )
#2840000000
0"
0%
#2850000000
1"
b01110 #
1%
b01110 '
b1111011011111011110010101110 (
b1110110111110111100101010101 )
#2860000000
0"
0%
#2870000000
1"
b10101 #
1%
b10101 '
b1110110111110111100101010101 (
b1101101111101111001010100011 )
#2880000000
0"
0%
#2890000000
1"
b00011 #
1%
b00011 '
b1101101111101111001010100011 (
b1011011111011110010101001111 )
#2900000000
0"
0%
#2910000000
1"
b01111 #
1%
b01111 '
b1011011111011110010101001111 (
b0110111110111100101010010111 )
#2920000000
0"
0%
#2930000000
1"
b10111 #
1%
b10111 '
b0110111110111100101010010111 (
b1101111101111001010100101110 )
#2940000000
0"
0%
#2950000000
1"
b01110 #
1%
b01110 '
b1101111101111001010100101110 (
b1011111011110010101001010101 )
#2960000000
0"
0%
#2970000000
1"
b10101 #
1%
b10101 '
b1011111011110010101001010101 (
b0111110111100101010010100011 )
#2980000000
0"
0%
#2990000000
1"
b00011 #
1%
b00011 '
b0111110111100101010010100011 (
b1111101111001010100101000110 )
#3000000000
0"
0%
#3010000000
1"
b00110 #
1%
b00110 '
b1111101111001010100101000110 (
b1111011110010101001010000101 )
#3020000000
0"
0%
#3030000000
1"
b00101 #
1%
b00101 '
b1111011110010101001010000101 (
b1110111100101010010100000011 )
#3040000000
0"
0%
#3050000000
1"
b00011 #
1%
b00011 '
b1110111100101010010100000011 (
b1101111001010100101000001111 )
#3060000000
0"
0%
#3070000000
1"
b01111 #
1%
b01111 '
b1101111001010100101000001111 (
b1011110010101001010000010111 )
#3080000000
0"
0%
#3090000000
1"
b10111 #
1%
b10111 '
b1011110010101001010000010111 (
b0111100101010010100000100111 )
#3100000000
0"
0%
#3110000000
1"
b00111 #
1%
b00111 '
b0111100101010010100000100111 (
b1111001010100101000001001110 )
#3120000000
0"
0%
#3130000000
1"
b01110 #
1%
b01110 '
b1111001010100101000001001110 (
b1110010101001010000010010101 )
#3140000000
0"
0%
#3150000000
1"
b10101 #
1%
b10101 '
b1110010101001010000010010101 (
b1100101010010100000100100011 )
#3160000000
0"
0%
#3170000000
1"
b00011 #
1%
b00011 '
b1100101010010100000100100011 (
b1001010100101000001001001111 )
#3180000000
0"
0%
#3190000000
1"
b01111 #
1%
b01111 '
b1001010100101000001001001111 (
b0010101001010000010010010111 )
#3200000000
0"
0%
#3210000000
1"
b10111 #
1%
b10111 '
b0010101001010000010010010111 (
b0101010010100000100100101110 )
#3220000000
0"
0%
#3230000000
1"
b01110 #
1%
b01110 '
b0101010010100000100100101110 (
b1010100101000001001001011100 )
#3240000000
0"
0%
#3250000000
1"
b11100 #
1%
b11100 '
b1010100101000001001001011100 (
b0101001010000010010010110001 )
#3260000000
0"
0%
#3270000000
1"
b10001 #
1%
b10001 '
b0101001010000010010010110001 (
b1010010100000100100101100010 )
#3280000000
0"
0%
#3290000000
1"
b00010 #
1%
b00010 '
b1010010100000100100101100010 (
b0100101000001001001011001101 )
#3300000000
0"
0%
#3310000000
1"
b01101 #
1%
b01101 '
b0100101000001001001011001101 (
b1001010000010010010110011010 )
#3320000000
0"
0%
#3330000000
1"
b11010 #
1%
b11010 '
b1001010000010010010110011010 (
b0010100000100100101100111101 )
#3340000000
0"
0%
#3350000000
1"
b11101 #
1%
b11101 '
b0010100000100100101100111101 (
b0101000001001001011001111010 )
#3360000000
0"
0%
#3370000000
1"
b11010 #
1%
b11010 '
b0101000001001001011001111010 (
b1010000010010010110011110100 )
#3380000000
0"
0%
#3390000000
1"
b10100 #
1%
b10100 '
b1010000010010010110011110100 (
b0100000100100101100111100001 )
#3400000000
0"
0%
#3410000000
1"
b00001 #
1%
b00001 '
b0100000100100101100111100001 (
b1000001001001011001111000010 )
#3420000000
0"
0%
#3430000000
1"
b00010 #
1%
b00010 '
b1000001001001011001111000010 (
b0000010010010110011110001101 )
#3440000000
0"
0%
#3450000000
1"
b01101 #
1%
b01101 '
b0000010010010110011110001101 (
b0000100100101100111100011010 )
#3460000000
0"
0%
#3470000000
1"
b11010 #
1%
b11010 '
b0000100100101100111100011010 (
b0001001001011001111000110100 )
#3480000000
0"
0%
#3490000000
1"
b10100 #
1%
b10100 '
b0001001001011001111000110100 (
b0010010010110011110001101000 )
#3500000000
0"
0%
#3510000000
1"
b01000 #
1%
b01000 '
b0010010010110011110001101000 (
b0100100101100111100011010000 )
#3520000000
0"
0%
#3530000000
1"
b10000 #
1%
b10000 '
b0100100101100111100011010000 (
b1001001011001111000110100000 )
#3540000000
0"
0%
#3550000000
1"
b00000 #
1%
b00000 '
b1001001011001111000110100000 (
b0010010110011110001101001001 )
#3560000000
0"
0%
#3570000000
1"
b01001 #
1%
b01001 '
b0010010110011110001101001001 (
b0100101100111100011010010010 )
#3580000000
0"
0%
#3590000000
1"
b10010 #
1%
b10010 '
b0100101100111100011010010010 (
b1001011001111000110100100100 )
#3600000000
0"
0%
#3610000000
1"
b00100 #
1%
b00100 '
b1001011001111000110100100100 (
b0010110011110001101001000001 )
#3620000000
0"
0%
#3630000000
1"
b00001 #
1%
b00001 '
b0010110011110001101001000001 (
b0101100111100011010010000010 )
#3640000000
0"
0%
#3650000000
1"
b00010 #
1%
b00010 '
b0101100111100011010010000010 (
b1011001111000110100100000100 )
#3660000000
0"
0%
#3670000000
1"
b00100 #
1%
b00100 '
b1011001111000110100100000100 (
b0110011110001101001000000001 )
#3680000000
0"
0%
#3690000000
1"
b00001 #
1%
b00001 '
b0110011110001101001000000001 (
b1100111100011010010000000010 )
#3700000000
0"
0%
#3710000000
1"
b00010 #
1%
b00010 '
b1100111100011010010000000010 (
b1001111000110100100000001101 )
#3720000000
0"
0%
#3730000000
1"
b01101 #
1%
b01101 '
b1001111000110100100000001101 (
b0011110001101001000000010011 )
#3740000000
0"
0%
#3750000000
1"
b10011 #
1%
b10011 '
b0011110001101001000000010011 (
b0111100011010010000000100110 )
#3760000000
0"
0%
#3770000000
1"
b00110 #
1%
b00110 '
b0111100011010010000000100110 (
b1111000110100100000001001100 )
#3780000000
0"
0%
#3790000000
1"
b01100 #
1%
b01100 '
b1111000110100100000001001100 (
b1110001101001000000010010001 )
#3800000000
0"
0%
#3810000000
1"
b10001 #
1%
b10001 '
b1110001101001000000010010001 (
b1100011010010000000100101011 )
#3820000000
0"
0%
#3830000000
1"
b01011 #
1%
b01011 '
b1100011010010000000100101011 (
b1000110100100000001001011111 )
#3840000000
0"
0%
#3850000000
1"
b11111 #
1%
b11111 '
b1000110100100000001001011111 (
b0001101001000000010010110111 )
#3860000000
0"
0%
#3870000000
1"
b10111 #
1%
b10111 '
b0001101001000000010010110111 (
b0011010010000000100101101110 )
#3880000000
0"
0%
#3890000000
1"
b01110 #
1%
b01110 '
b0011010010000000100101101110 (
b0110100100000001001011011100 )
#3900000000
0"
0%
#3910000000
1"
b11100 #
1%
b11100 '
b0110100100000001001011011100 (
b1101001000000010010110111000 )
#3920000000
0"
0%
#3930000000
1"
b11000 #
1%
b11000 '
b1101001000000010010110111000 (
b1010010000000100101101111001 )
#3940000000
0"
0%
#3950000000
1"
b11001 #
1%
b11001 '
b1010010000000100101101111001 (
b0100100000001001011011111011 )
#3960000000
0"
0%
#3970000000
1"
b11011 #
1%
b11011 '
b0100100000001001011011111011 (
b1001000000010010110111110110 )
#3980000000
0"
0%
#3990000000
1"
b10110 #
1%
b10110 '
b1001000000010010110111110110 (
b0010000000100101101111100101 )
#4000000000
0"
0%
#4010000000
1"
b00101 #
1%
b00101 '
b0010000000100101101111100101 (
b0100000001001011011111001010 )
#4020000000
0"
0%
#4030000000
1"
b01010 #
1%
b01010 '
b0100000001001011011111001010 (
b1000000010010110111110010100 )
#4040000000
0"
0%
#4050000000
1"
b10100 #
1%
b10100 '
b1000000010010110111110010100 (
b0000000100101101111100100001 )
#4060000000
0"
0%
#4070000000
1"
b00001 #
1%
b00001 '
b0000000100101101111100100001 (
b0000001001011011111001000010 )
#4080000000
0"
0%
#4090000000
1"
b00010 #
1%
b00010 '
b0000001001011011111001000010 (
b0000010010110111110010000100 )
#4100000000
0"
0%
#4110000000
1"
b00100 #
1%
b00100 '
b0000010010110111110010000100 (
b0000100101101111100100001000 )
#4120000000
0"
0%
#4130000000
1"
b01000 #
1%
b01000 '
b0000100101101111100100001000 (
b0001001011011111001000010000 )
#4140000000
0"
0%
#4150000000
1"
b10000 #
1%
b10000 '
b0001001011011111001000010000 (
b0010010110111110010000100000 )
#4160000000
0"
0%
#4170000000
1"
b00000 #
1%
b00000 '
b0010010110111110010000100000 (
b0100101101111100100001000000 )
